grifter/__init__.py
grifter/api.py
grifter/cli.py
grifter/config.yml
grifter/constants.py
grifter/custom_filters.py
grifter/defaults.yml
grifter/loaders.py
grifter/utils.py
grifter/validators.py
grifter/examples/groups-example.yml
grifter/examples/guest-defaults.yml
grifter/examples/guests-example.yml
grifter/examples/veos-guests.yml
grifter/examples/vmx-guests.yml
grifter/examples/vqfx-guests.yml
grifter/examples/vsrx-guests.yml
grifter/schemas/guest-config-schema.yml
grifter/schemas/guest-pairs-schema.yml
grifter/schemas/guest-schema.yml
grifter/templates/additional-data-storage-trigger.j2
grifter/templates/base.j2
grifter/templates/blackhole-interfaces-trigger.j2
grifter/templates/get-mac.rb
grifter/templates/guest.j2
grifter/templates/libvirt-config.j2
grifter/templates/libvirt-data-interface-config.j2
grifter/templates/libvirt-internal-interface-config.j2
grifter/templates/libvirt-reserved-interface-config.j2
grifter/templates/throttle-cpu-trigger.j2
grifter/templates/topology.dot.j2
tests/__init__.py
tests/mock_data.py
tests/test_api.py
tests/test_cli.py
tests/test_constants.py
tests/test_custom_filters.py
tests/test_defaults.py
tests/test_loaders.py
tests/test_render.py
tests/test_utils.py
tests/test_validators.py
grifter-0.2.11.dist-info/LICENSE
grifter-0.2.11.dist-info/METADATA
grifter-0.2.11.dist-info/WHEEL
grifter-0.2.11.dist-info/entry_points.txt
grifter-0.2.11.dist-info/top_level.txt
grifter-0.2.11.dist-info/RECORD
