Metadata-Version: 2.1
Name: grifter
Version: 0.2.11
Summary: A package to generate Vagrantfiles for use with Vagrant.
Home-page: UNKNOWN
Author: Brad Searle
Author-email: bradleysearle@gmail.com
License: GNU GENERAL PUBLIC LICENSE Version 3
Platform: UNKNOWN
Requires-Dist: jinja2
Requires-Dist: pyyaml
Requires-Dist: click
Requires-Dist: cerberus
